keyword2cmdline.py
keyword2cmdline-2.0.1.dist-info/LICENSE
keyword2cmdline-2.0.1.dist-info/METADATA
keyword2cmdline-2.0.1.dist-info/WHEEL
keyword2cmdline-2.0.1.dist-info/top_level.txt
keyword2cmdline-2.0.1.dist-info/RECORD
