Metadata-Version: 2.1
Name: keyword2cmdline
Version: 2.0.1
Summary: Keyword arguments of a function as command-line arguments
Home-page: https://github.com/wecacuee/keyword2cmdline
Author: Vikas Dhiman
Author-email: wecacuee@github.com
License: MIT
Platform: UNKNOWN
Classifier: Development Status :: 3 - Alpha
Classifier: Programming Language :: Python :: 3
Classifier: License :: OSI Approved :: MIT License
Classifier: Operating System :: OS Independent
Requires-Python: >=3.5
Requires-Dist: kwplus
Provides-Extra: argcomplete
Requires-Dist: argcomplete ; extra == 'argcomplete'
